{"data":{"blocks":[{"@type":"@builder.io/sdk:Element","id":"builder-meriidff0tq9xy5njhk","tagName":"div","meta":{"naturalWidth":784},"responsiveStyles":{"large":{"color":"oklch(0.792 0.209 151.711)","fontFamily":"ui-monospace, SFMono-Regular, Menlo, Monaco, Consolas, \"Liberation Mono\", \"Courier New\", monospace","maxWidth":"784px","paddingLeft":"28px","paddingRight":"28px","textDecorationColor":"oklch(0.792 0.209 151.711)","textEmphasisColor":"oklch(0.792 0.209 151.711)","backgroundColor":"oklab(0.208 -0.00310889 -0.0418848 / 0.5)"}},"properties":{},"children":[{"@type":"@builder.io/sdk:Element","id":"builder-meriidgb0cn7twi3tktq","tagName":"div","responsiveStyles":{"large":{"color":"oklch(0.792 0.209 151.711)","fontFamily":"ui-monospace, SFMono-Regular, Menlo, Monaco, Consolas, \"Liberation Mono\", \"Courier New\", monospace","marginBottom":"56px","textAlign":"center","textDecorationColor":"oklch(0.792 0.209 151.711)","textEmphasisColor":"oklch(0.792 0.209 151.711)"}},"properties":{},"children":[{"@type":"@builder.io/sdk:Element","id":"builder-meriidgl01f9ynihu0eu","tagName":"span","responsiveStyles":{"large":{"color":"oklch(0.789 0.154 211.53)","display":"inline","fontFamily":"ui-monospace, SFMono-Regular, Menlo, Monaco, Consolas, \"Liberation Mono\", \"Courier New\", monospace","fontSize":"12.25px","lineHeight":"17.5px","textAlign":"center","textDecorationColor":"oklch(0.789 0.154 211.53)","textEmphasisColor":"oklch(0.789 0.154 211.53)"}},"properties":{},"children":[{"@type":"@builder.io/sdk:Element","tagName":"span","component":{"name":"Text","options":{"text":"$ ./load_faq_database"}}}]},{"@type":"@builder.io/sdk:Element","id":"builder-meriidgr0rkrh9ok828t","tagName":"h2","responsiveStyles":{"large":{"color":"oklch(0.792 0.209 151.711)","fontFamily":"ui-monospace, SFMono-Regular, Menlo, Monaco, Consolas, \"Liberation Mono\", \"Courier New\", monospace","fontSize":"31.5px","fontWeight":"700","lineHeight":"35px","marginBottom":"21px","marginTop":"14px","textAlign":"center","textDecorationColor":"oklch(0.792 0.209 151.711)","textEmphasisColor":"oklch(0.792 0.209 151.711)"}},"properties":{},"children":[{"@type":"@builder.io/sdk:Element","tagName":"span","component":{"name":"Text","options":{"text":"FREQUENTLY ASKED QUESTIONS"}}}]}]},{"@type":"@builder.io/sdk:Element","id":"builder-meriidgz0rbg3qqgrfv","tagName":"div","responsiveStyles":{"large":{"color":"oklch(0.792 0.209 151.711)","fontFamily":"ui-monospace, SFMono-Regular, Menlo, Monaco, Consolas, \"Liberation Mono\", \"Courier New\", monospace","textDecorationColor":"oklch(0.792 0.209 151.711)","textEmphasisColor":"oklch(0.792 0.209 151.711)"}},"properties":{},"children":[{"@type":"@builder.io/sdk:Element","id":"builder-meriidh60om77x06jujd","tagName":"div","responsiveStyles":{"large":{"backgroundColor":"oklch(0.279 0.041 260.031)","borderBottom":"0.8px solid oklab(0.715 -0.116822 -0.0824726 / 0.3)","borderBottomLeftRadius":"8.75px","borderBottomRightRadius":"8.75px","borderBottomWidth":"0.8px","borderColor":"oklab(0.715 -0.116822 -0.0824726 / 0.3)","borderRadius":"8.75px","borderTopLeftRadius":"8.75px","borderTopRightRadius":"8.75px","color":"oklch(0.792 0.209 151.711)","fontFamily":"ui-monospace, SFMono-Regular, Menlo, Monaco, Consolas, \"Liberation Mono\", \"Courier New\", monospace","marginBottom":"14px","paddingLeft":"21px","paddingRight":"21px","textDecorationColor":"oklch(0.792 0.209 151.711)","textEmphasisColor":"oklch(0.792 0.209 151.711)"}},"properties":{},"children":[{"@type":"@builder.io/sdk:Element","id":"builder-meriidhg0n0mjdyp5ejg","tagName":"h3","responsiveStyles":{"large":{"color":"oklch(0.792 0.209 151.711)","display":"flex","fontFamily":"ui-monospace, SFMono-Regular, Menlo, Monaco, Consolas, \"Liberation Mono\", \"Courier New\", monospace","textDecorationColor":"oklch(0.792 0.209 151.711)","textEmphasisColor":"oklch(0.792 0.209 151.711)"}},"properties":{},"children":[{"@type":"@builder.io/sdk:Element","id":"builder-meriidhn05brojo1x6hv","tagName":"button","responsiveStyles":{"large":{"alignItems":"flex-start","appearance":"button","borderBottomLeftRadius":"6.75px","borderBottomRightRadius":"6.75px","borderRadius":"6.75px","borderTopLeftRadius":"6.75px","borderTopRightRadius":"6.75px","color":"oklch(0.792 0.209 151.711)","cursor":"default","display":"flex","flexBasis":"0%","flexGrow":"1","fontFamily":"ui-monospace, SFMono-Regular, Menlo, Monaco, Consolas, \"Liberation Mono\", \"Courier New\", monospace","fontSize":"12.25px","fontWeight":"500","gap":"14px","gridGap":"14px","gridRowGap":"14px","justifyContent":"space-between","lineHeight":"17.5px","paddingBottom":"14px","paddingTop":"14px","rowGap":"14px","textDecorationColor":"oklch(0.792 0.209 151.711)","textEmphasisColor":"oklch(0.792 0.209 151.711)","transitionDuration":"0.15s","transitionTimingFunction":"cubic-bezier(0.4, 0, 0.2, 1)","backgroundColor":"rgba(0, 0, 0, 0)","borderColor":"rgba(0, 0, 0, 0)"},"medium":{"borderColor":"rgba(0, 0, 0, 0.1)"}},"properties":{"type":"button","aria-controls":"radix-:rl:","aria-expanded":"false"},"children":[{"@type":"@builder.io/sdk:Element","tagName":"span","component":{"name":"Text","options":{"text":"How accurate is the AI estimate feature?"}}},{"@type":"@builder.io/sdk:Element","id":"builder-meriidhw00ljczfa4lca9","tagName":"div","component":{"name":"Custom Code","options":{"code":"<svg xmlns=\"http://www.w3.org/2000/svg\" width=\"24\" height=\"24\" viewBox=\"0 0 24 24\" fill=\"none\" stroke=\"currentColor\" stroke-width=\"2\" stroke-linecap=\"round\" stroke-linejoin=\"round\" class=\"lucide lucide-chevron-down text-muted-foreground pointer-events-none size-4 shrink-0 translate-y-0.5 transition-transform duration-200\" style=\"\n  color: rgb(113, 113, 130);\n  cursor: default;\n  fill: none;\n  flex-shrink: 0;\n  font-family: ui-monospace, SFMono-Regular, Menlo, Monaco, Consolas, &quot;Liberation Mono&quot;, &quot;Courier New&quot;, monospace;\n  font-size: 12.25px;\n  font-weight: 500;\n  height: 24px;\n  line-height: 17.5px;\n  overflow-clip-margin: content-box;\n  overflow-x: hidden;\n  overflow-y: hidden;\n  pointer-events: none;\n  stroke: rgb(113, 113, 130);\n  stroke-linecap: round;\n  stroke-linejoin: round;\n  stroke-width: 2px;\n  text-decoration-color: rgb(113, 113, 130);\n  text-emphasis-color: rgb(113, 113, 130);\n  transition-duration: 0.2s;\n  transition-property: transform, translate, scale, rotate;\n  transition-timing-function: cubic-bezier(0.4, 0, 0.2, 1);\n  translate: 0px 1.75px;\n  vertical-align: middle;\n  width: 24px;\"><path d=\"m6 9 6 6 6-6\"></path></svg>"}},"layerName":"SVG","responsiveStyles":{"large":{"color":"rgb(113, 113, 130)","cursor":"default","fill":"none","flexShrink":"0","fontFamily":"ui-monospace, SFMono-Regular, Menlo, Monaco, Consolas, \"Liberation Mono\", \"Courier New\", monospace","fontSize":"12.25px","fontWeight":"500","height":"24px","lineHeight":"17.5px","overflowClipMargin":"content-box","overflowX":"hidden","overflowY":"hidden","pointerEvents":"none","stroke":"rgb(113, 113, 130)","strokeLinecap":"round","strokeLinejoin":"round","strokeWidth":"2px","textDecorationColor":"rgb(113, 113, 130)","textEmphasisColor":"rgb(113, 113, 130)","transitionDuration":"0.2s","transitionProperty":"transform, translate, scale, rotate","transitionTimingFunction":"cubic-bezier(0.4, 0, 0.2, 1)","translate":"0px 1.75px","verticalAlign":"middle","width":"24px"}},"properties":{"xmlns":"http://www.w3.org/2000/svg","width":"24","height":"24","viewBox":"0 0 24 24","fill":"none","stroke":"currentColor","stroke-width":"2","stroke-linecap":"round","stroke-linejoin":"round"},"children":[]}]}]},{"@type":"@builder.io/sdk:Element","id":"builder-meriidi40egva836qvvc","tagName":"div","responsiveStyles":{"large":{"animation":"0.2s ease-out 0s 1 normal none running accordion-up","animationDuration":"0.2s","animationName":"accordion-up","animationTimingFunction":"ease-out","color":"oklch(0.792 0.209 151.711)","display":"none","fontFamily":"ui-monospace, SFMono-Regular, Menlo, Monaco, Consolas, \"Liberation Mono\", \"Courier New\", monospace","fontSize":"12.25px","lineHeight":"17.5px","overflowX":"hidden","overflowY":"hidden","textDecorationColor":"oklch(0.792 0.209 151.711)","textEmphasisColor":"oklch(0.792 0.209 151.711)"}},"properties":{"hidden":"","role":"region","aria-labelledby":"radix-:rk:"},"children":[]}]},{"@type":"@builder.io/sdk:Element","id":"builder-meriidic08ykedlb5dgr","tagName":"div","responsiveStyles":{"large":{"backgroundColor":"oklch(0.279 0.041 260.031)","borderBottom":"0.8px solid oklab(0.715 -0.116822 -0.0824726 / 0.3)","borderBottomLeftRadius":"8.75px","borderBottomRightRadius":"8.75px","borderBottomWidth":"0.8px","borderColor":"oklab(0.715 -0.116822 -0.0824726 / 0.3)","borderRadius":"8.75px","borderTopLeftRadius":"8.75px","borderTopRightRadius":"8.75px","color":"oklch(0.792 0.209 151.711)","fontFamily":"ui-monospace, SFMono-Regular, Menlo, Monaco, Consolas, \"Liberation Mono\", \"Courier New\", monospace","marginBottom":"14px","paddingLeft":"21px","paddingRight":"21px","textDecorationColor":"oklch(0.792 0.209 151.711)","textEmphasisColor":"oklch(0.792 0.209 151.711)"}},"properties":{},"children":[{"@type":"@builder.io/sdk:Element","id":"builder-meriidik0rmb1q9dj5c","tagName":"h3","responsiveStyles":{"large":{"color":"oklch(0.792 0.209 151.711)","display":"flex","fontFamily":"ui-monospace, SFMono-Regular, Menlo, Monaco, Consolas, \"Liberation Mono\", \"Courier New\", monospace","textDecorationColor":"oklch(0.792 0.209 151.711)","textEmphasisColor":"oklch(0.792 0.209 151.711)"}},"properties":{},"children":[{"@type":"@builder.io/sdk:Element","id":"builder-meriidit0uepq7bsi0up","tagName":"button","responsiveStyles":{"large":{"alignItems":"flex-start","appearance":"button","borderBottomLeftRadius":"6.75px","borderBottomRightRadius":"6.75px","borderRadius":"6.75px","borderTopLeftRadius":"6.75px","borderTopRightRadius":"6.75px","color":"oklch(0.792 0.209 151.711)","cursor":"default","display":"flex","flexBasis":"0%","flexGrow":"1","fontFamily":"ui-monospace, SFMono-Regular, Menlo, Monaco, Consolas, \"Liberation Mono\", \"Courier New\", monospace","fontSize":"12.25px","fontWeight":"500","gap":"14px","gridGap":"14px","gridRowGap":"14px","justifyContent":"space-between","lineHeight":"17.5px","paddingBottom":"14px","paddingTop":"14px","rowGap":"14px","textDecorationColor":"oklch(0.792 0.209 151.711)","textEmphasisColor":"oklch(0.792 0.209 151.711)","transitionDuration":"0.15s","transitionTimingFunction":"cubic-bezier(0.4, 0, 0.2, 1)","backgroundColor":"rgba(0, 0, 0, 0)","borderColor":"rgba(0, 0, 0, 0)"},"medium":{"borderColor":"rgba(0, 0, 0, 0.1)"}},"properties":{"type":"button","aria-controls":"radix-:rn:","aria-expanded":"false"},"children":[{"@type":"@builder.io/sdk:Element","tagName":"span","component":{"name":"Text","options":{"text":"What areas do you serve in Northeast Arkansas?"}}},{"@type":"@builder.io/sdk:Element","id":"builder-meriidj20ki9gumaxnwp","tagName":"div","component":{"name":"Custom Code","options":{"code":"<svg xmlns=\"http://www.w3.org/2000/svg\" width=\"24\" height=\"24\" viewBox=\"0 0 24 24\" fill=\"none\" stroke=\"currentColor\" stroke-width=\"2\" stroke-linecap=\"round\" stroke-linejoin=\"round\" class=\"lucide lucide-chevron-down text-muted-foreground pointer-events-none size-4 shrink-0 translate-y-0.5 transition-transform duration-200\" style=\"\n  color: rgb(113, 113, 130);\n  cursor: default;\n  fill: none;\n  flex-shrink: 0;\n  font-family: ui-monospace, SFMono-Regular, Menlo, Monaco, Consolas, &quot;Liberation Mono&quot;, &quot;Courier New&quot;, monospace;\n  font-size: 12.25px;\n  font-weight: 500;\n  height: 24px;\n  line-height: 17.5px;\n  overflow-clip-margin: content-box;\n  overflow-x: hidden;\n  overflow-y: hidden;\n  pointer-events: none;\n  stroke: rgb(113, 113, 130);\n  stroke-linecap: round;\n  stroke-linejoin: round;\n  stroke-width: 2px;\n  text-decoration-color: rgb(113, 113, 130);\n  text-emphasis-color: rgb(113, 113, 130);\n  transition-duration: 0.2s;\n  transition-property: transform, translate, scale, rotate;\n  transition-timing-function: cubic-bezier(0.4, 0, 0.2, 1);\n  translate: 0px 1.75px;\n  vertical-align: middle;\n  width: 24px;\"><path d=\"m6 9 6 6 6-6\"></path></svg>"}},"layerName":"SVG","responsiveStyles":{"large":{"color":"rgb(113, 113, 130)","cursor":"default","fill":"none","flexShrink":"0","fontFamily":"ui-monospace, SFMono-Regular, Menlo, Monaco, Consolas, \"Liberation Mono\", \"Courier New\", monospace","fontSize":"12.25px","fontWeight":"500","height":"24px","lineHeight":"17.5px","overflowClipMargin":"content-box","overflowX":"hidden","overflowY":"hidden","pointerEvents":"none","stroke":"rgb(113, 113, 130)","strokeLinecap":"round","strokeLinejoin":"round","strokeWidth":"2px","textDecorationColor":"rgb(113, 113, 130)","textEmphasisColor":"rgb(113, 113, 130)","transitionDuration":"0.2s","transitionProperty":"transform, translate, scale, rotate","transitionTimingFunction":"cubic-bezier(0.4, 0, 0.2, 1)","translate":"0px 1.75px","verticalAlign":"middle","width":"24px"}},"properties":{"xmlns":"http://www.w3.org/2000/svg","width":"24","height":"24","viewBox":"0 0 24 24","fill":"none","stroke":"currentColor","stroke-width":"2","stroke-linecap":"round","stroke-linejoin":"round"},"children":[]}]}]},{"@type":"@builder.io/sdk:Element","id":"builder-meriidjc0o53s67cjrj9","tagName":"div","responsiveStyles":{"large":{"animation":"0.2s ease-out 0s 1 normal none running accordion-up","animationDuration":"0.2s","animationName":"accordion-up","animationTimingFunction":"ease-out","color":"oklch(0.792 0.209 151.711)","display":"none","fontFamily":"ui-monospace, SFMono-Regular, Menlo, Monaco, Consolas, \"Liberation Mono\", \"Courier New\", monospace","fontSize":"12.25px","lineHeight":"17.5px","overflowX":"hidden","overflowY":"hidden","textDecorationColor":"oklch(0.792 0.209 151.711)","textEmphasisColor":"oklch(0.792 0.209 151.711)"}},"properties":{"hidden":"","role":"region","aria-labelledby":"radix-:rm:"},"children":[]}]},{"@type":"@builder.io/sdk:Element","id":"builder-meriidjj0zppybwj7l6","tagName":"div","responsiveStyles":{"large":{"backgroundColor":"oklch(0.279 0.041 260.031)","borderBottom":"0.8px solid oklab(0.715 -0.116822 -0.0824726 / 0.3)","borderBottomLeftRadius":"8.75px","borderBottomRightRadius":"8.75px","borderBottomWidth":"0.8px","borderColor":"oklab(0.715 -0.116822 -0.0824726 / 0.3)","borderRadius":"8.75px","borderTopLeftRadius":"8.75px","borderTopRightRadius":"8.75px","color":"oklch(0.792 0.209 151.711)","fontFamily":"ui-monospace, SFMono-Regular, Menlo, Monaco, Consolas, \"Liberation Mono\", \"Courier New\", monospace","marginBottom":"14px","paddingLeft":"21px","paddingRight":"21px","textDecorationColor":"oklch(0.792 0.209 151.711)","textEmphasisColor":"oklch(0.792 0.209 151.711)"}},"properties":{},"children":[{"@type":"@builder.io/sdk:Element","id":"builder-meriidjq0gfb45r5pvr","tagName":"h3","responsiveStyles":{"large":{"color":"oklch(0.792 0.209 151.711)","display":"flex","fontFamily":"ui-monospace, SFMono-Regular, Menlo, Monaco, Consolas, \"Liberation Mono\", \"Courier New\", monospace","textDecorationColor":"oklch(0.792 0.209 151.711)","textEmphasisColor":"oklch(0.792 0.209 151.711)"}},"properties":{},"children":[{"@type":"@builder.io/sdk:Element","id":"builder-meriidjw0thpum1ynw9b","tagName":"button","responsiveStyles":{"large":{"alignItems":"flex-start","appearance":"button","borderBottomLeftRadius":"6.75px","borderBottomRightRadius":"6.75px","borderRadius":"6.75px","borderTopLeftRadius":"6.75px","borderTopRightRadius":"6.75px","color":"oklch(0.792 0.209 151.711)","cursor":"default","display":"flex","flexBasis":"0%","flexGrow":"1","fontFamily":"ui-monospace, SFMono-Regular, Menlo, Monaco, Consolas, \"Liberation Mono\", \"Courier New\", monospace","fontSize":"12.25px","fontWeight":"500","gap":"14px","gridGap":"14px","gridRowGap":"14px","justifyContent":"space-between","lineHeight":"17.5px","paddingBottom":"14px","paddingTop":"14px","rowGap":"14px","textDecorationColor":"oklch(0.792 0.209 151.711)","textEmphasisColor":"oklch(0.792 0.209 151.711)","transitionDuration":"0.15s","transitionTimingFunction":"cubic-bezier(0.4, 0, 0.2, 1)","backgroundColor":"rgba(0, 0, 0, 0)","borderColor":"rgba(0, 0, 0, 0)"},"medium":{"borderColor":"rgba(0, 0, 0, 0.1)"}},"properties":{"type":"button","aria-controls":"radix-:rp:","aria-expanded":"false"},"children":[{"@type":"@builder.io/sdk:Element","tagName":"span","component":{"name":"Text","options":{"text":"Do you provide free estimates?"}}},{"@type":"@builder.io/sdk:Element","id":"builder-meriidk102oqxd0u5858","tagName":"div","component":{"name":"Custom Code","options":{"code":"<svg xmlns=\"http://www.w3.org/2000/svg\" width=\"24\" height=\"24\" viewBox=\"0 0 24 24\" fill=\"none\" stroke=\"currentColor\" stroke-width=\"2\" stroke-linecap=\"round\" stroke-linejoin=\"round\" class=\"lucide lucide-chevron-down text-muted-foreground pointer-events-none size-4 shrink-0 translate-y-0.5 transition-transform duration-200\" style=\"\n  color: rgb(113, 113, 130);\n  cursor: default;\n  fill: none;\n  flex-shrink: 0;\n  font-family: ui-monospace, SFMono-Regular, Menlo, Monaco, Consolas, &quot;Liberation Mono&quot;, &quot;Courier New&quot;, monospace;\n  font-size: 12.25px;\n  font-weight: 500;\n  height: 24px;\n  line-height: 17.5px;\n  overflow-clip-margin: content-box;\n  overflow-x: hidden;\n  overflow-y: hidden;\n  pointer-events: none;\n  stroke: rgb(113, 113, 130);\n  stroke-linecap: round;\n  stroke-linejoin: round;\n  stroke-width: 2px;\n  text-decoration-color: rgb(113, 113, 130);\n  text-emphasis-color: rgb(113, 113, 130);\n  transition-duration: 0.2s;\n  transition-property: transform, translate, scale, rotate;\n  transition-timing-function: cubic-bezier(0.4, 0, 0.2, 1);\n  translate: 0px 1.75px;\n  vertical-align: middle;\n  width: 24px;\"><path d=\"m6 9 6 6 6-6\"></path></svg>"}},"layerName":"SVG","responsiveStyles":{"large":{"color":"rgb(113, 113, 130)","cursor":"default","fill":"none","flexShrink":"0","fontFamily":"ui-monospace, SFMono-Regular, Menlo, Monaco, Consolas, \"Liberation Mono\", \"Courier New\", monospace","fontSize":"12.25px","fontWeight":"500","height":"24px","lineHeight":"17.5px","overflowClipMargin":"content-box","overflowX":"hidden","overflowY":"hidden","pointerEvents":"none","stroke":"rgb(113, 113, 130)","strokeLinecap":"round","strokeLinejoin":"round","strokeWidth":"2px","textDecorationColor":"rgb(113, 113, 130)","textEmphasisColor":"rgb(113, 113, 130)","transitionDuration":"0.2s","transitionProperty":"transform, translate, scale, rotate","transitionTimingFunction":"cubic-bezier(0.4, 0, 0.2, 1)","translate":"0px 1.75px","verticalAlign":"middle","width":"24px"}},"properties":{"xmlns":"http://www.w3.org/2000/svg","width":"24","height":"24","viewBox":"0 0 24 24","fill":"none","stroke":"currentColor","stroke-width":"2","stroke-linecap":"round","stroke-linejoin":"round"},"children":[]}]}]},{"@type":"@builder.io/sdk:Element","id":"builder-meriidk80x4rl4rupsab","tagName":"div","responsiveStyles":{"large":{"animation":"0.2s ease-out 0s 1 normal none running accordion-up","animationDuration":"0.2s","animationName":"accordion-up","animationTimingFunction":"ease-out","color":"oklch(0.792 0.209 151.711)","display":"none","fontFamily":"ui-monospace, SFMono-Regular, Menlo, Monaco, Consolas, \"Liberation Mono\", \"Courier New\", monospace","fontSize":"12.25px","lineHeight":"17.5px","overflowX":"hidden","overflowY":"hidden","textDecorationColor":"oklch(0.792 0.209 151.711)","textEmphasisColor":"oklch(0.792 0.209 151.711)"}},"properties":{"hidden":"","role":"region","aria-labelledby":"radix-:ro:"},"children":[]}]},{"@type":"@builder.io/sdk:Element","id":"builder-meriidke0a9l56arywpa","tagName":"div","responsiveStyles":{"large":{"backgroundColor":"oklch(0.279 0.041 260.031)","borderBottom":"0.8px solid oklab(0.715 -0.116822 -0.0824726 / 0.3)","borderBottomLeftRadius":"8.75px","borderBottomRightRadius":"8.75px","borderBottomWidth":"0.8px","borderColor":"oklab(0.715 -0.116822 -0.0824726 / 0.3)","borderRadius":"8.75px","borderTopLeftRadius":"8.75px","borderTopRightRadius":"8.75px","color":"oklch(0.792 0.209 151.711)","fontFamily":"ui-monospace, SFMono-Regular, Menlo, Monaco, Consolas, \"Liberation Mono\", \"Courier New\", monospace","marginBottom":"14px","paddingLeft":"21px","paddingRight":"21px","textDecorationColor":"oklch(0.792 0.209 151.711)","textEmphasisColor":"oklch(0.792 0.209 151.711)"}},"properties":{},"children":[{"@type":"@builder.io/sdk:Element","id":"builder-meriidkk06x10iywjr1v","tagName":"h3","responsiveStyles":{"large":{"color":"oklch(0.792 0.209 151.711)","display":"flex","fontFamily":"ui-monospace, SFMono-Regular, Menlo, Monaco, Consolas, \"Liberation Mono\", \"Courier New\", monospace","textDecorationColor":"oklch(0.792 0.209 151.711)","textEmphasisColor":"oklch(0.792 0.209 151.711)"}},"properties":{},"children":[{"@type":"@builder.io/sdk:Element","id":"builder-meriidkp0oawj1cw0npd","tagName":"button","responsiveStyles":{"large":{"alignItems":"flex-start","appearance":"button","borderBottomLeftRadius":"6.75px","borderBottomRightRadius":"6.75px","borderRadius":"6.75px","borderTopLeftRadius":"6.75px","borderTopRightRadius":"6.75px","color":"oklch(0.792 0.209 151.711)","cursor":"default","display":"flex","flexBasis":"0%","flexGrow":"1","fontFamily":"ui-monospace, SFMono-Regular, Menlo, Monaco, Consolas, \"Liberation Mono\", \"Courier New\", monospace","fontSize":"12.25px","fontWeight":"500","gap":"14px","gridGap":"14px","gridRowGap":"14px","justifyContent":"space-between","lineHeight":"17.5px","paddingBottom":"14px","paddingTop":"14px","rowGap":"14px","textDecorationColor":"oklch(0.792 0.209 151.711)","textEmphasisColor":"oklch(0.792 0.209 151.711)","transitionDuration":"0.15s","transitionTimingFunction":"cubic-bezier(0.4, 0, 0.2, 1)","backgroundColor":"rgba(0, 0, 0, 0)","borderColor":"rgba(0, 0, 0, 0)"},"medium":{"borderColor":"rgba(0, 0, 0, 0.1)"}},"properties":{"type":"button","aria-controls":"radix-:rr:","aria-expanded":"false"},"children":[{"@type":"@builder.io/sdk:Element","tagName":"span","component":{"name":"Text","options":{"text":"Are you licensed and insured?"}}},{"@type":"@builder.io/sdk:Element","id":"builder-meriidkv0wqmuc2aom6i","tagName":"div","component":{"name":"Custom Code","options":{"code":"<svg xmlns=\"http://www.w3.org/2000/svg\" width=\"24\" height=\"24\" viewBox=\"0 0 24 24\" fill=\"none\" stroke=\"currentColor\" stroke-width=\"2\" stroke-linecap=\"round\" stroke-linejoin=\"round\" class=\"lucide lucide-chevron-down text-muted-foreground pointer-events-none size-4 shrink-0 translate-y-0.5 transition-transform duration-200\" style=\"\n  color: rgb(113, 113, 130);\n  cursor: default;\n  fill: none;\n  flex-shrink: 0;\n  font-family: ui-monospace, SFMono-Regular, Menlo, Monaco, Consolas, &quot;Liberation Mono&quot;, &quot;Courier New&quot;, monospace;\n  font-size: 12.25px;\n  font-weight: 500;\n  height: 24px;\n  line-height: 17.5px;\n  overflow-clip-margin: content-box;\n  overflow-x: hidden;\n  overflow-y: hidden;\n  pointer-events: none;\n  stroke: rgb(113, 113, 130);\n  stroke-linecap: round;\n  stroke-linejoin: round;\n  stroke-width: 2px;\n  text-decoration-color: rgb(113, 113, 130);\n  text-emphasis-color: rgb(113, 113, 130);\n  transition-duration: 0.2s;\n  transition-property: transform, translate, scale, rotate;\n  transition-timing-function: cubic-bezier(0.4, 0, 0.2, 1);\n  translate: 0px 1.75px;\n  vertical-align: middle;\n  width: 24px;\"><path d=\"m6 9 6 6 6-6\"></path></svg>"}},"layerName":"SVG","responsiveStyles":{"large":{"color":"rgb(113, 113, 130)","cursor":"default","fill":"none","flexShrink":"0","fontFamily":"ui-monospace, SFMono-Regular, Menlo, Monaco, Consolas, \"Liberation Mono\", \"Courier New\", monospace","fontSize":"12.25px","fontWeight":"500","height":"24px","lineHeight":"17.5px","overflowClipMargin":"content-box","overflowX":"hidden","overflowY":"hidden","pointerEvents":"none","stroke":"rgb(113, 113, 130)","strokeLinecap":"round","strokeLinejoin":"round","strokeWidth":"2px","textDecorationColor":"rgb(113, 113, 130)","textEmphasisColor":"rgb(113, 113, 130)","transitionDuration":"0.2s","transitionProperty":"transform, translate, scale, rotate","transitionTimingFunction":"cubic-bezier(0.4, 0, 0.2, 1)","translate":"0px 1.75px","verticalAlign":"middle","width":"24px"}},"properties":{"xmlns":"http://www.w3.org/2000/svg","width":"24","height":"24","viewBox":"0 0 24 24","fill":"none","stroke":"currentColor","stroke-width":"2","stroke-linecap":"round","stroke-linejoin":"round"},"children":[]}]}]},{"@type":"@builder.io/sdk:Element","id":"builder-meriidl20gdi2xhc51i","tagName":"div","responsiveStyles":{"large":{"animation":"0.2s ease-out 0s 1 normal none running accordion-up","animationDuration":"0.2s","animationName":"accordion-up","animationTimingFunction":"ease-out","color":"oklch(0.792 0.209 151.711)","display":"none","fontFamily":"ui-monospace, SFMono-Regular, Menlo, Monaco, Consolas, \"Liberation Mono\", \"Courier New\", monospace","fontSize":"12.25px","lineHeight":"17.5px","overflowX":"hidden","overflowY":"hidden","textDecorationColor":"oklch(0.792 0.209 151.711)","textEmphasisColor":"oklch(0.792 0.209 151.711)"}},"properties":{"hidden":"","role":"region","aria-labelledby":"radix-:rq:"},"children":[]}]},{"@type":"@builder.io/sdk:Element","id":"builder-meriidl80kjy5m5oik8r","tagName":"div","responsiveStyles":{"large":{"backgroundColor":"oklch(0.279 0.041 260.031)","borderBottomLeftRadius":"8.75px","borderBottomRightRadius":"8.75px","borderColor":"oklab(0.715 -0.116822 -0.0824726 / 0.3)","borderRadius":"8.75px","borderTopLeftRadius":"8.75px","borderTopRightRadius":"8.75px","color":"oklch(0.792 0.209 151.711)","fontFamily":"ui-monospace, SFMono-Regular, Menlo, Monaco, Consolas, \"Liberation Mono\", \"Courier New\", monospace","paddingLeft":"21px","paddingRight":"21px","textDecorationColor":"oklch(0.792 0.209 151.711)","textEmphasisColor":"oklch(0.792 0.209 151.711)"}},"properties":{},"children":[{"@type":"@builder.io/sdk:Element","id":"builder-meriidle0kb7gbgpc3eg","tagName":"h3","responsiveStyles":{"large":{"color":"oklch(0.792 0.209 151.711)","display":"flex","fontFamily":"ui-monospace, SFMono-Regular, Menlo, Monaco, Consolas, \"Liberation Mono\", \"Courier New\", monospace","textDecorationColor":"oklch(0.792 0.209 151.711)","textEmphasisColor":"oklch(0.792 0.209 151.711)"}},"properties":{},"children":[{"@type":"@builder.io/sdk:Element","id":"builder-meriidlm084cfdjgsqi","tagName":"button","responsiveStyles":{"large":{"alignItems":"flex-start","appearance":"button","borderBottomLeftRadius":"6.75px","borderBottomRightRadius":"6.75px","borderRadius":"6.75px","borderTopLeftRadius":"6.75px","borderTopRightRadius":"6.75px","color":"oklch(0.792 0.209 151.711)","cursor":"default","display":"flex","flexBasis":"0%","flexGrow":"1","fontFamily":"ui-monospace, SFMono-Regular, Menlo, Monaco, Consolas, \"Liberation Mono\", \"Courier New\", monospace","fontSize":"12.25px","fontWeight":"500","gap":"14px","gridGap":"14px","gridRowGap":"14px","justifyContent":"space-between","lineHeight":"17.5px","paddingBottom":"14px","paddingTop":"14px","rowGap":"14px","textDecorationColor":"oklch(0.792 0.209 151.711)","textEmphasisColor":"oklch(0.792 0.209 151.711)","transitionDuration":"0.15s","transitionTimingFunction":"cubic-bezier(0.4, 0, 0.2, 1)","backgroundColor":"rgba(0, 0, 0, 0)","borderColor":"rgba(0, 0, 0, 0)"},"medium":{"borderColor":"rgba(0, 0, 0, 0.1)"}},"properties":{"type":"button","aria-controls":"radix-:rt:","aria-expanded":"false"},"children":[{"@type":"@builder.io/sdk:Element","tagName":"span","component":{"name":"Text","options":{"text":"What payment methods do you accept?"}}},{"@type":"@builder.io/sdk:Element","id":"builder-meriidlt0nx7g94rklts","tagName":"div","component":{"name":"Custom Code","options":{"code":"<svg xmlns=\"http://www.w3.org/2000/svg\" width=\"24\" height=\"24\" viewBox=\"0 0 24 24\" fill=\"none\" stroke=\"currentColor\" stroke-width=\"2\" stroke-linecap=\"round\" stroke-linejoin=\"round\" class=\"lucide lucide-chevron-down text-muted-foreground pointer-events-none size-4 shrink-0 translate-y-0.5 transition-transform duration-200\" style=\"\n  color: rgb(113, 113, 130);\n  cursor: default;\n  fill: none;\n  flex-shrink: 0;\n  font-family: ui-monospace, SFMono-Regular, Menlo, Monaco, Consolas, &quot;Liberation Mono&quot;, &quot;Courier New&quot;, monospace;\n  font-size: 12.25px;\n  font-weight: 500;\n  height: 24px;\n  line-height: 17.5px;\n  overflow-clip-margin: content-box;\n  overflow-x: hidden;\n  overflow-y: hidden;\n  pointer-events: none;\n  stroke: rgb(113, 113, 130);\n  stroke-linecap: round;\n  stroke-linejoin: round;\n  stroke-width: 2px;\n  text-decoration-color: rgb(113, 113, 130);\n  text-emphasis-color: rgb(113, 113, 130);\n  transition-duration: 0.2s;\n  transition-property: transform, translate, scale, rotate;\n  transition-timing-function: cubic-bezier(0.4, 0, 0.2, 1);\n  translate: 0px 1.75px;\n  vertical-align: middle;\n  width: 24px;\"><path d=\"m6 9 6 6 6-6\"></path></svg>"}},"layerName":"SVG","responsiveStyles":{"large":{"color":"rgb(113, 113, 130)","cursor":"default","fill":"none","flexShrink":"0","fontFamily":"ui-monospace, SFMono-Regular, Menlo, Monaco, Consolas, \"Liberation Mono\", \"Courier New\", monospace","fontSize":"12.25px","fontWeight":"500","height":"24px","lineHeight":"17.5px","overflowClipMargin":"content-box","overflowX":"hidden","overflowY":"hidden","pointerEvents":"none","stroke":"rgb(113, 113, 130)","strokeLinecap":"round","strokeLinejoin":"round","strokeWidth":"2px","textDecorationColor":"rgb(113, 113, 130)","textEmphasisColor":"rgb(113, 113, 130)","transitionDuration":"0.2s","transitionProperty":"transform, translate, scale, rotate","transitionTimingFunction":"cubic-bezier(0.4, 0, 0.2, 1)","translate":"0px 1.75px","verticalAlign":"middle","width":"24px"}},"properties":{"xmlns":"http://www.w3.org/2000/svg","width":"24","height":"24","viewBox":"0 0 24 24","fill":"none","stroke":"currentColor","stroke-width":"2","stroke-linecap":"round","stroke-linejoin":"round"},"children":[]}]}]},{"@type":"@builder.io/sdk:Element","id":"builder-meriidm106v6pnapklme","tagName":"div","responsiveStyles":{"large":{"animation":"0.2s ease-out 0s 1 normal none running accordion-up","animationDuration":"0.2s","animationName":"accordion-up","animationTimingFunction":"ease-out","color":"oklch(0.792 0.209 151.711)","display":"none","fontFamily":"ui-monospace, SFMono-Regular, Menlo, Monaco, Consolas, \"Liberation Mono\", \"Courier New\", monospace","fontSize":"12.25px","lineHeight":"17.5px","overflowX":"hidden","overflowY":"hidden","textDecorationColor":"oklch(0.792 0.209 151.711)","textEmphasisColor":"oklch(0.792 0.209 151.711)"}},"properties":{"hidden":"","role":"region","aria-labelledby":"radix-:rs:"},"children":[]}]}]}]}]}}